Workbook

Sheet Как читать
A1: Экономика SevastopolAI · City Code · YuRichRWA — v1.1 от 2026-10-25
A2: Источник правды — economics/params.json. Этот файл собирается скриптом economics/build_model.py.
A3: Жёлтое — вводные (можно менять здесь, но потом перенеси в params.json). Зелёное — итоги. Всё остальное — формулы.
A4: Проверка: python tools/check.py — пересчитывает этот файл независимым движком и сверяет с economics/model.py до копейки.
A5: Оборот партнёров ≠ наша выручка. Сценарии — модель, не факт. Зарплата основателя не учтена.
A7: Листы: Параметры → Расчёт (юнит-экономика до копейки) → Сценарии S1–S5 → XP → Доли партнёров.

Sheet Параметры
A1: Ключ | B1: Параметр | C1: Ед. | D1: Значение | E1: Статус | F1: Источник
B2: City Code · членство
A3: price_basic | B3: Basic, в год | C3: ₽ | D3: 5108 | E3: решение | F3: City Code v1.0, п.3
A4: price_founder | B4: «Основатели», в год | C4: ₽ | D4: 15108 | E4: решение | F4: City Code v1.0, п.3
A5: seats_basic | B5: Мест Basic в первом транше | C5: шт | D5: 250 | E5: решение | F5: v1.0, п.4
A6: seats_founder | B6: Мест «Основатели» в первом транше | C6: шт | D6: 50 | E6: решение | F6: v1.0, п.4
A7: days_year | B7: Дней в году членства | C7: дн | D7: 365 | E7: факт | F7: срок 12 месяцев, v1.0
A8: partners_signed | B8: Подписано партнёров сейчас | C8: шт | D8: 0 | E8: допущение | F8: обновляй после каждого подписания
A9: refund_days_used | B9: Пример возврата: прошло дней | C9: дн | D9: 90 | E9: допущение | F9: пример для оферты
B10: Расход участника и привилегии
A11: spend | B11: Средний расход участника у партнёров | C11: ₽/мес | D11: 7000 | E11: допущение | F11: v1.0, п.6 — проверить отчётами партнёров
A12: priv_min | B12: Привилегия минимум | C12: % | D12: 0.03 | E12: решение | F12: v1.0, п.5
A13: priv_avg | B13: Привилегия в среднем | C13: % | D13: 0.05 | E13: допущение | F13: середина 3–7%
A14: priv_max | B14: Привилегия максимум | C14: % | D14: 0.07 | E14: решение | F14: v1.0, п.5
B15: Партнёр
A16: partner_fee | B16: Вход партнёра в первом транше | C16: ₽ | D16: 0 | E16: решение | F16: v1.0, п.5: без платы за вход и без комиссии
A17: partner_turnover | B17: Допустимый доп. оборот партнёра от клуба | C17: ₽/мес | D17: 105000 | E17: допущение | F17: спросить у партнёра при подписании; 105 000 = 15 мест
A18: partner_margin | B18: Маржинальность партнёра (выручка минус себестоимость) | C18: % | D18: 0.6 | E18: допущение | F18: кафе ~60–70%, розница ~30% — подставь своё
A19: partner_new_share | B19: Доля клубного оборота, которой без клуба не было бы | C19: % | D19: 0.3 | E19: допущение | F19: проверить на пилоте
A20: partner_exit_days | B20: Уведомление о выходе партнёра | C20: дн | D20: 14 | E20: решение | F20: v1.1
B21: Налоги и приём платежей
A22: npd_ind | B22: НПД с физлиц | C22: % | D22: 0.04 | E22: факт | F22: 422-ФЗ; ставки 2026 не менялись (naloger.ru, kontur.ru)
A23: npd_biz | B23: НПД с ИП и юрлиц | C23: % | D23: 0.06 | E23: факт | F23: 422-ФЗ
A24: npd_limit | B24: Лимит дохода НПД | C24: ₽/год | D24: 2400000 | E24: факт | F24: 422-ФЗ, п.8 ч.2 ст.4; режим до 31.12.2028
A25: usn | B25: УСН «доходы» | C25: % | D25: 0.06 | E25: факт | F25: НК РФ ст.346.20
A26: ip_fixed | B26: Фикс. взносы ИП за себя, 2026 | C26: ₽/год | D26: 57390 | E26: факт | F26: nalog.gov.ru, ст.430 НК
A27: ip_extra | B27: Доп. взнос ИП с дохода сверх 300 000 | C27: % | D27: 0.01 | E27: факт | F27: ст.430 НК
A28: ip_extra_from | B28: Порог доп. взноса | C28: ₽/год | D28: 300000 | E28: факт | F28: ст.430 НК
A29: acq_sbp | B29: СБП (потолок ЦБ для бизнеса) | C29: % | D29: 0.007 | E29: факт | F29: ЦБ: не выше 0,7%; НДС на перевод не начисляется
A30: acq_card | B30: Карты через ЮKassa (базовый тариф) | C30: % | D30: 0.035 | E30: факт | F30: yookassa.ru/docs/support/payments/fees
A31: acq_vat | B31: НДС на комиссию за карты с 2026 | C31: % | D31: 0.22 | E31: факт | F31: 425-ФЗ; ЮKassa удерживает 22% от комиссии
A32: sbp_share | B32: Доля оплат по СБП | C32: % | D32: 0.5 | E32: допущение | F32: проси платить по СБП — это дешевле в 6 раз
A33: ad_levy | B33: Отчисление с интернет-рекламы | C33: % | D33: 0.03 | E33: факт | F33: ст.18.2 «О рекламе», с 01.04.2025
B34: Мерч (себестоимость — оценка, уточнить у подрядчика)
A35: passport_price | B35: Физический паспорт, цена | C35: ₽ | D35: 1500 | E35: решение | F35: прайс v1.0-документа
A36: passport_cost | B36: Физический паспорт, себестоимость | C36: ₽ | D36: 400 | E36: допущение | F36: оценка, запросить у типографии
A37: keychain_price | B37: Брелок «6 ключей», цена | C37: ₽ | D37: 1200 | E37: решение
A38: keychain_cost | B38: Брелок, себестоимость | C38: ₽ | D38: 425 | E38: допущение | F38: середина 350–500
A39: hoodie_price | B39: Худи, цена | C39: ₽ | D39: 4900 | E39: решение
A40: hoodie_cost | B40: Худи, себестоимость | C40: ₽ | D40: 2250 | E40: допущение | F40: середина 2 000–2 500
B41: Реклама Sevastopol AI
A42: ad_views_post | B42: Средний охват поста в канале | C42: просм. | D42: 800 | E42: допущение | F42: подставь факт из статистики канала за 30 дней
A43: ad_views_card | B43: Показов карточки «Рекомендуем» за 7 дней | C43: показ | D43: 300 | E43: допущение | F43: смотри /admin: открытия категории за неделю
A44: ad_cpm | B44: Цена 1 000 просмотров (городская аудитория) | C44: ₽ | D44: 1500 | E44: допущение | F44: ориентир для локальных каналов; пересматривать раз в квартал
A45: ad_min_post | B45: Минимум за пост | C45: ₽ | D45: 1000 | E45: решение | F45: v1.1: работа с текстом и маркировкой
A46: ad_min_card | B46: Минимум за «Рекомендуем» 7 дней | C46: ₽ | D46: 1000 | E46: решение | F46: v1.1
A47: ad_guide_place | B47: Подборка: за одно место | C47: ₽ | D47: 1000 | E47: решение | F47: v1.1
A48: ad_guide_min | B48: Подборка: минимум мест | C48: шт | D48: 3 | E48: решение | F48: v1.1
A49: ad_route | B49: Включение в маршрут (если реально по пути) | C49: ₽ | D49: 2000 | E49: решение | F49: v1.1
A50: ad_event | B50: Анонс события | C50: ₽ | D50: 1000 | E50: решение | F50: партнёру 1 в месяц бесплатно
A51: ad_partner_disc | B51: Скидка партнёру City Code на рекламу | C51: % | D51: 0.5 | E51: решение | F51: v1.1
A52: shoot_price | B52: Съёмка заведения | C52: ₽ | D52: 12000 | E52: решение | F52: себестоимость 40% — поэтому партнёру не −50%
A53: shoot_partner | B53: Съёмка для партнёра | C53: ₽ | D53: 8000 | E53: решение
A54: shoot_cost | B54: Себестоимость съёмки (доля оператора/оборудования) | C54: % | D54: 0.4 | E54: решение | F54: договор с партнёром по оборудованию
B55: XP и награды (значения живут в коде бота, здесь — для расчётов)
A56: xp_grant | B56: XP для ранга City Code | C56: XP | D56: 7000 | E56: решение | F56: бот: CITYCODE_GRANT_XP
A57: grant_days | B57: Грант за ранг City Code | C57: дн | D57: 365 | E57: решение | F57: v1.1 (было 180) — бот: CITYCODE_GRANT_DAYS
A58: grant_quota | B58: Квота грантов от мест транша | C58: % | D58: 0.1 | E58: решение | F58: бот: CITYCODE_GRANT_QUOTA = 30
A59: ref_days | B59: Участнику за оплатившего приглашённого | C59: дн | D59: 30 | E59: решение | F59: бот: MEMBER_REFERRAL_PAID_DAYS
A60: ref_max | B60: Оплативших приглашённых в год с бонусом | C60: шт | D60: 6 | E60: решение | F60: бот: MEMBER_REFERRAL_PAID_MAX_PER_YEAR
A61: xp_daily_cap | B61: Потолок XP за кнопки в день | C61: XP | D61: 10 | E61: решение | F61: бот: DAILY_ACTIVITY_CAP

Sheet Расчёт
A1: Ключ | B1: Показатель | C1: Ед. | D1: Значение | E1: Как считается | F1: Формула
B2: Членство: цена в день, комиссия, налог, сколько остаётся
A3: basic_month | B3: Basic в месяц | C3: ₽ | D3: =ROUND('Параметры'!$D$3/12,2) | E3: цена ÷ 12 | F3: ROUND({price_basic}/12,2)
A4: basic_day | B4: Basic в день | C4: ₽ | D4: =ROUND('Параметры'!$D$3/'Параметры'!$D$7,2) | E4: цена ÷ 365 | F4: ROUND({price_basic}/{days_year},2)
A5: founder_month | B5: «Основатели» в месяц | C5: ₽ | D5: =ROUND('Параметры'!$D$4/12,2) | E5: цена ÷ 12 | F5: ROUND({price_founder}/12,2)
A6: founder_day | B6: «Основатели» в день | C6: ₽ | D6: =ROUND('Параметры'!$D$4/'Параметры'!$D$7,2) | E6: цена ÷ 365 | F6: ROUND({price_founder}/{days_year},2)
A7: acq_card_eff | B7: Карты: комиссия с НДС | C7: % | D7: ='Параметры'!$D$30*(1+'Параметры'!$D$31) | E7: 3,5% × 1,22 | F7: {acq_card}*(1+{acq_vat})
A8: acq_blend | B8: Комиссия в среднем (доля СБП из параметров) | C8: % | D8: ='Параметры'!$D$32*'Параметры'!$D$29+(1-'Параметры'!$D$32)*$D$7 | E8: смесь СБП и карт | F8: {sbp_share}*{acq_sbp}+(1-{sbp_share})*{acq_card_eff}
A9: basic_fee_sbp | B9: Basic: комиссия СБП | C9: ₽ | D9: =ROUND('Параметры'!$D$3*'Параметры'!$D$29,2) | E9: 5 108 × 0,7% | F9: ROUND({price_basic}*{acq_sbp},2)
A10: basic_fee_card | B10: Basic: комиссия карты | C10: ₽ | D10: =ROUND('Параметры'!$D$3*$D$7,2) | E10: 5 108 × 4,27% | F10: ROUND({price_basic}*{acq_card_eff},2)
A11: basic_tax_npd | B11: Basic: налог НПД 4% | C11: ₽ | D11: =ROUND('Параметры'!$D$3*'Параметры'!$D$22,2) | E11: с полной суммы | F11: ROUND({price_basic}*{npd_ind},2)
A12: basic_tax_usn | B12: Basic: налог УСН 6% (если ИП) | C12: ₽ | D12: =ROUND('Параметры'!$D$3*'Параметры'!$D$25,2) | E12: до вычета взносов | F12: ROUND({price_basic}*{usn},2)
A13: basic_net_npd_sbp | B13: Basic: остаётся (НПД + СБП) | C13: ₽ | D13: ='Параметры'!$D$3-$D$9-$D$11 | E13: основной вариант | F13: {price_basic}-{basic_fee_sbp}-{basic_tax_npd}
A14: basic_net_npd_card | B14: Basic: остаётся (НПД + карта) | C14: ₽ | D14: ='Параметры'!$D$3-$D$10-$D$11 | E14: если платят картой | F14: {price_basic}-{basic_fee_card}-{basic_tax_npd}
A15: basic_net_usn_sbp | B15: Basic: остаётся (ИП УСН + СБП) | C15: ₽ | D15: ='Параметры'!$D$3-$D$9-$D$12 | E15: после перехода на ИП | F15: {price_basic}-{basic_fee_sbp}-{basic_tax_usn}
A16: founder_kit_cost | B16: «Основатели»: себестоимость набора (паспорт + брелок) | C16: ₽ | D16: ='Параметры'!$D$36+'Параметры'!$D$38 | E16: выдаём физически | F16: {passport_cost}+{keychain_cost}
A17: founder_kit_retail | B17: «Основатели»: набор по рознице | C17: ₽ | D17: ='Параметры'!$D$35+'Параметры'!$D$37 | E17: что человек получает в рублях | F17: {passport_price}+{keychain_price}
A18: founder_fee_sbp | B18: «Основатели»: комиссия СБП | C18: ₽ | D18: =ROUND('Параметры'!$D$4*'Параметры'!$D$29,2) | F18: ROUND({price_founder}*{acq_sbp},2)
A19: founder_tax_npd | B19: «Основатели»: налог НПД 4% | C19: ₽ | D19: =ROUND('Параметры'!$D$4*'Параметры'!$D$22,2) | F19: ROUND({price_founder}*{npd_ind},2)
A20: founder_net_npd_sbp | B20: «Основатели»: остаётся (НПД + СБП − набор) | C20: ₽ | D20: ='Параметры'!$D$4-$D$18-$D$19-$D$16 | F20: {price_founder}-{founder_fee_sbp}-{founder_tax_npd}-{founder_kit_cost}
A21: founder_extra | B21: «Основатели» дороже Basic на | C21: ₽ | D21: ='Параметры'!$D$4-'Параметры'!$D$3 | F21: {price_founder}-{price_basic}
A22: tranche_seats | B22: Мест в транше | C22: шт | D22: ='Параметры'!$D$5+'Параметры'!$D$6 | E22: 250 + 50 | F22: {seats_basic}+{seats_founder}
A23: tranche_gross | B23: Транш: выручка | C23: ₽ | D23: ='Параметры'!$D$5*'Параметры'!$D$3+'Параметры'!$D$6*'Параметры'!$D$4 | E23: 250 × 5 108 + 50 × 15 108 | F23: {seats_basic}*{price_basic}+{seats_founder}*{price_founder}
A24: tranche_net_npd_sbp | B24: Транш: остаётся (НПД + СБП − наборы) | C24: ₽ | D24: ='Параметры'!$D$5*$D$13+'Параметры'!$D$6*$D$20 | F24: {seats_basic}*{basic_net_npd_sbp}+{seats_founder}*{founder_net_npd_sbp}
A25: npd_headroom | B25: Запас до лимита НПД в год продажи транша | C25: ₽ | D25: ='Параметры'!$D$24-$D$23 | E25: всё сверх — уже ИП | F25: {npd_limit}-{tranche_gross}
A26: v10_typo | B26: Ошибка годовой модели v1.0 (300 × 5 108) | C26: ₽ | D26: =$D$23-$D$22*'Параметры'!$D$3 | E26: v1.0 недосчитал | F26: {tranche_gross}-{tranche_seats}*{price_basic}
B27: Честно для участника: сколько возвращают привилегии
A28: saving_min | B28: Экономия в год при 3% | C28: ₽ | D28: ='Параметры'!$D$11*12*'Параметры'!$D$12 | E28: 7 000 × 12 × 3% | F28: {spend}*12*{priv_min}
A29: saving_avg | B29: Экономия в год при 5% | C29: ₽ | D29: ='Параметры'!$D$11*12*'Параметры'!$D$13 | E29: 7 000 × 12 × 5% | F29: {spend}*12*{priv_avg}
A30: saving_max | B30: Экономия в год при 7% | C30: ₽ | D30: ='Параметры'!$D$11*12*'Параметры'!$D$14 | E30: 7 000 × 12 × 7% | F30: {spend}*12*{priv_max}
A31: payback_avg | B31: Привилегии при 5% возвращают от цены Basic | C31: % | D31: =ROUND($D$29/'Параметры'!$D$3,4) | E31: остальное — события и люди | F31: ROUND({saving_avg}/{price_basic},4)
A32: breakeven_min | B32: Basic окупается привилегиями при расходе (3%) | C32: ₽ | D32: =ROUND('Параметры'!$D$3/12/'Параметры'!$D$12,2) | E32: в месяц | F32: ROUND({price_basic}/12/{priv_min},2)
A33: breakeven_avg | B33: Basic окупается привилегиями при расходе (5%) | C33: ₽ | D33: =ROUND('Параметры'!$D$3/12/'Параметры'!$D$13,2) | E33: в месяц | F33: ROUND({price_basic}/12/{priv_avg},2)
A34: breakeven_max | B34: Basic окупается привилегиями при расходе (7%) | C34: ₽ | D34: =ROUND('Параметры'!$D$3/12/'Параметры'!$D$14,2) | E34: в месяц | F34: ROUND({price_basic}/12/{priv_max},2)
A35: founder_breakeven_avg | B35: «Основатели» окупаются привилегиями при расходе (5%) | C35: ₽ | D35: =ROUND('Параметры'!$D$4/12/'Параметры'!$D$13,2) | E35: в месяц — это статус, не скидка | F35: ROUND({price_founder}/12/{priv_avg},2)
B36: Честно для партнёра: что стоит привилегия и что даёт клуб
A37: seats_per_partner | B37: Мест на одного партнёра | C37: шт | D37: =FLOOR('Параметры'!$D$17/'Параметры'!$D$11,1) | E37: доп. оборот ÷ расход участника (правило v1.0) | F37: FLOOR({partner_turnover}/{spend},1)
A38: partner_priv_cost | B38: Партнёр отдаёт привилегией в месяц | C38: ₽ | D38: ='Параметры'!$D$17*'Параметры'!$D$13 | E38: оборот × 5% | F38: {partner_turnover}*{priv_avg}
A39: partner_new_profit | B39: Партнёр получает маржи с новых гостей в месяц | C39: ₽ | D39: ='Параметры'!$D$17*'Параметры'!$D$19*'Параметры'!$D$18 | E39: оборот × доля новых × маржа | F39: {partner_turnover}*{partner_new_share}*{partner_margin}
A40: partner_gain | B40: Итог партнёра в месяц | C40: ₽ | D40: =$D$39-$D$38 | F40: {partner_new_profit}-{partner_priv_cost}
A41: partner_gain_year | B41: Итог партнёра в год | C41: ₽ | D41: =$D$40*12 | F41: {partner_gain}*12
A42: partner_breakeven_share | B42: Партнёр в плюсе, если новых гостей не меньше | C42: % | D42: =ROUND('Параметры'!$D$13/'Параметры'!$D$18,4) | E42: привилегия ÷ маржа | F42: ROUND({priv_avg}/{partner_margin},4)
A43: partners_for_founders | B43: Партнёров нужно, чтобы открыть 50 мест «Основатели» | C43: шт | D43: =CEILING('Параметры'!$D$6/$D$37,1) | F43: CEILING({seats_founder}/{seats_per_partner},1)
A44: partners_for_tranche | B44: Партнёров нужно на весь транш | C44: шт | D44: =CEILING($D$22/$D$37,1) | E44: это два «С» логотипа | F44: CEILING({tranche_seats}/{seats_per_partner},1)
A45: seats_open | B45: Можно продать мест сейчас | C45: шт | D45: =MIN($D$22,'Параметры'!$D$8*$D$37) | E45: 15 × подписанные партнёры | F45: MIN({tranche_seats},{partners_signed}*{seats_per_partner})
A46: club_turnover_full | B46: Оборот клуба у партнёров при 300 участниках | C46: ₽ | D46: =$D$22*'Параметры'!$D$11 | E46: в месяц, это НЕ наш доход | F46: {tranche_seats}*{spend}
B47: Возврат (ст. 32 ЗоЗПП): пропорционально дням минус фактические расходы
A48: refund_days_left | B48: Пример: осталось дней | C48: дн | D48: ='Параметры'!$D$7-'Параметры'!$D$9 | F48: {days_year}-{refund_days_used}
A49: refund_basic_unused | B49: Basic: стоимость неиспользованных дней | C49: ₽ | D49: =ROUND('Параметры'!$D$3*$D$48/'Параметры'!$D$7,2) | F49: ROUND({price_basic}*{refund_days_left}/{days_year},2)
A50: refund_basic | B50: Basic: к возврату | C50: ₽ | D50: =MAX(0,$D$49-$D$9) | E50: минус комиссия, которую уже взяли | F50: MAX(0,{refund_basic_unused}-{basic_fee_sbp})
A51: refund_founder_unused | B51: «Основатели»: стоимость неиспользованных дней | C51: ₽ | D51: =ROUND('Параметры'!$D$4*$D$48/'Параметры'!$D$7,2) | F51: ROUND({price_founder}*{refund_days_left}/{days_year},2)
A52: refund_founder | B52: «Основатели»: к возврату | C52: ₽ | D52: =MAX(0,$D$51-$D$18-$D$16) | E52: минус комиссия и себестоимость выданного набора | F52: MAX(0,{refund_founder_unused}-{founder_fee_sbp}-{founder_kit_cost})
B53: XP и приглашения в рублях
A54: ref_bonus_value | B54: +30 дней за оплатившего приглашённого стоят | C54: ₽ | D54: =ROUND('Параметры'!$D$3*'Параметры'!$D$59/'Параметры'!$D$7,2) | E54: 5 108 × 30 ÷ 365 | F54: ROUND({price_basic}*{ref_days}/{days_year},2)
A55: ref_bonus_share | B55: Это от цены Basic | C55: % | D55: =ROUND($D$54/'Параметры'!$D$3,4) | E55: как комиссия за привод | F55: ROUND({ref_bonus_value}/{price_basic},4)
A56: ref_bonus_year_max | B56: Максимум в год на одного участника (6 приглашённых) | C56: ₽ | D56: =ROUND('Параметры'!$D$3*'Параметры'!$D$59*'Параметры'!$D$60/'Параметры'!$D$7,2) | F56: ROUND({price_basic}*{ref_days}*{ref_max}/{days_year},2)
A57: grant_value | B57: Грант за 7000 XP стоит | C57: ₽ | D57: =ROUND('Параметры'!$D$3*'Параметры'!$D$57/'Параметры'!$D$7,2) | E57: 12 месяцев Basic | F57: ROUND({price_basic}*{grant_days}/{days_year},2)
A58: grant_seats | B58: Грантов на транш максимум | C58: шт | D58: =FLOOR($D$22*'Параметры'!$D$58,1) | E58: 10% мест | F58: FLOOR({tranche_seats}*{grant_quota},1)
A59: grant_max_forgone | B59: Недополученная выручка, если все гранты заняты и транш продан | C59: ₽ | D59: =$D$58*$D$57 | E59: раньше чем через ~14 месяцев не наступит | F59: {grant_seats}*{grant_value}
A60: grant_min_days | B60: Минимум дней одними кнопками до 7000 | C60: дн | D60: =CEILING(('Параметры'!$D$56-10)/'Параметры'!$D$61,1) | E60: старт паспорта = 10 XP | F60: CEILING(({xp_grant}-10)/{xp_daily_cap},1)
B61: Реклама: цена = охват × CPM, но не ниже минимума
A62: ad_post | B62: Пост в канале | C62: ₽ | D62: =MAX('Параметры'!$D$45,ROUND('Параметры'!$D$42*'Параметры'!$D$44/1000,-2)) | E62: охват × CPM ÷ 1000, до сотни | F62: MAX({ad_min_post},ROUND({ad_views_post}*{ad_cpm}/1000,-2))
A63: ad_post_p | B63: Пост — партнёру | C63: ₽ | D63: =ROUND($D$62*(1-'Параметры'!$D$51),2) | E63: −50% | F63: ROUND({ad_post}*(1-{ad_partner_disc}),2)
A64: ad_card | B64: «Рекомендуем» в категории, 7 дней | C64: ₽ | D64: =MAX('Параметры'!$D$46,ROUND('Параметры'!$D$43*'Параметры'!$D$44/1000,-2)) | E64: показы × CPM ÷ 1000 | F64: MAX({ad_min_card},ROUND({ad_views_card}*{ad_cpm}/1000,-2))
A65: ad_card_p | B65: «Рекомендуем» — партнёру | C65: ₽ | D65: =ROUND($D$64*(1-'Параметры'!$D$51),2) | F65: ROUND({ad_card}*(1-{ad_partner_disc}),2)
A66: ad_guide | B66: Подборка (3 места) | C66: ₽ | D66: ='Параметры'!$D$47*'Параметры'!$D$48 | E66: +1 000 за каждое место сверх | F66: {ad_guide_place}*{ad_guide_min}
A67: ad_guide_p | B67: Подборка — партнёру | C67: ₽ | D67: =ROUND($D$66*(1-'Параметры'!$D$51),2) | F67: ROUND({ad_guide}*(1-{ad_partner_disc}),2)
A68: ad_route_p | B68: Маршрут — партнёру | C68: ₽ | D68: =ROUND('Параметры'!$D$49*(1-'Параметры'!$D$51),2) | F68: ROUND({ad_route}*(1-{ad_partner_disc}),2)
A69: ad_event_p | B69: Анонс — партнёру (после бесплатного в месяц) | C69: ₽ | D69: =ROUND('Параметры'!$D$50*(1-'Параметры'!$D$51),2) | F69: ROUND({ad_event}*(1-{ad_partner_disc}),2)
A70: ad_post_net | B70: Пост: остаётся (НПД 6% с бизнеса + 3% сбор) | C70: ₽ | D70: =$D$62-ROUND($D$62*'Параметры'!$D$23,2)-ROUND($D$62*'Параметры'!$D$33,2) | E70: оплата переводом, без эквайринга | F70: {ad_post}-ROUND({ad_post}*{npd_biz},2)-ROUND({ad_post}*{ad_levy},2)
A71: ad_post_p_net | B71: Пост партнёру: остаётся | C71: ₽ | D71: =$D$63-ROUND($D$63*'Параметры'!$D$23,2)-ROUND($D$63*'Параметры'!$D$33,2) | F71: {ad_post_p}-ROUND({ad_post_p}*{npd_biz},2)-ROUND({ad_post_p}*{ad_levy},2)
A72: shoot_net | B72: Съёмка: остаётся | C72: ₽ | D72: ='Параметры'!$D$52*(1-'Параметры'!$D$54)-ROUND('Параметры'!$D$52*'Параметры'!$D$23,2) | E72: минус 40% оператору и 6% | F72: {shoot_price}*(1-{shoot_cost})-ROUND({shoot_price}*{npd_biz},2)
A73: shoot_partner_net | B73: Съёмка партнёру: остаётся | C73: ₽ | D73: ='Параметры'!$D$53*(1-'Параметры'!$D$54)-ROUND('Параметры'!$D$53*'Параметры'!$D$23,2) | F73: {shoot_partner}*(1-{shoot_cost})-ROUND({shoot_partner}*{npd_biz},2)
B74: Мерч: только через ИП (самозанятый не может перепродавать товары)
A75: passport_net | B75: Физический паспорт: остаётся | C75: ₽ | D75: ='Параметры'!$D$35-ROUND('Параметры'!$D$35*'Параметры'!$D$29,2)-ROUND('Параметры'!$D$35*'Параметры'!$D$25,2)-'Параметры'!$D$36 | E75: СБП, УСН 6%, себестоимость | F75: {passport_price}-ROUND({passport_price}*{acq_sbp},2)-ROUND({passport_price}*{usn},2)-{passport_cost}
A76: keychain_net | B76: Брелок: остаётся | C76: ₽ | D76: ='Параметры'!$D$37-ROUND('Параметры'!$D$37*'Параметры'!$D$29,2)-ROUND('Параметры'!$D$37*'Параметры'!$D$25,2)-'Параметры'!$D$38 | F76: {keychain_price}-ROUND({keychain_price}*{acq_sbp},2)-ROUND({keychain_price}*{usn},2)-{keychain_cost}
A77: hoodie_net | B77: Худи: остаётся | C77: ₽ | D77: ='Параметры'!$D$39-ROUND('Параметры'!$D$39*'Параметры'!$D$29,2)-ROUND('Параметры'!$D$39*'Параметры'!$D$25,2)-'Параметры'!$D$40 | F77: {hoodie_price}-ROUND({hoodie_price}*{acq_sbp},2)-ROUND({hoodie_price}*{usn},2)-{hoodie_cost}

Sheet Сценарии
A1: Сценарии роста. Жёлтое — вводные сценария; цены, налоги и комиссии берутся из «Параметры» и «Расчёт».
A3: Показатель | B3: Ед. | C3: S1 · Пилот | D3: S2 · Сеть | E3: S3 · Город | F3: S4 · Зрелый город | G3: S5 · 3 города
C4: 5 партнёров · 100 MAU | D4: 10 партнёров · 500 MAU | E4: 30 партнёров · 5 000 MAU | F4: 60 партнёров · 15 000 MAU | G4: 150 партнёров · 50 000 MAU
A5: ВВОДНЫЕ СЦЕНАРИЯ
A6: Партнёров (точек) | B6: шт | C6: 5 | D6: 10 | E6: 30 | F6: 60 | G6: 150
A7: Пользователей бота в месяц (MAU) | B7: чел | C7: 100 | D7: 500 | E7: 5000 | F7: 15000 | G7: 50000
A8: Мест «Основатели» всего | B8: шт | C8: 50 | D8: 50 | E8: 50 | F8: 50 | G8: 150 | H8: 50 на город
A9: Конверсия MAU → участник | B9: % | C9: 0.05 | D9: 0.04 | E9: 0.035 | F9: 0.03 | G9: 0.03 | H9: проверить на пилоте
A10: Участники из личных продаж | B10: чел | C10: 10 | D10: 30 | E10: 60 | F10: 80 | G10: 150 | H10: Основатели продаются руками
A11: Взнос партнёра v2.0 (не принято — решение владельца) | B11: ₽/мес | C11: 0 | D11: 0 | E11: 3000 | F11: 3000 | G11: 3000 | H11: v1.0 разрешает «в последующих версиях»; вводить только после отчёта, что партнёр в плюсе
A12: Платных размещений SAI в месяц | B12: шт | C12: 2 | D12: 5 | E12: 12 | F12: 20 | G12: 40 | H12: не чаще 1 рекламы на 6–8 своих постов
A13: Охват поста | B13: просм. | C13: 800 | D13: 1500 | E13: 4000 | F13: 8000 | G13: 15000 | H13: ≈25–30% подписчиков канала; цена = охват × CPM, не ниже минимума
A14: Доля размещений от партнёров (−50%) | B14: % | C14: 0.5 | D14: 0.5 | E14: 0.5 | F14: 0.5 | G14: 0.5
A15: Съёмок в месяц | B15: шт | C15: 0 | D15: 2 | E15: 4 | F15: 8 | G15: 20
A16: Платных событий в месяц | B16: шт | C16: 0 | D16: 1 | E16: 2 | F16: 4 | G16: 10
A17: Гостей на событии | B17: чел | C17: 0 | D17: 20 | E17: 35 | F17: 50 | G17: 50
A18: Билет | B18: ₽ | C18: 1500 | D18: 1500 | E18: 2000 | F18: 2000 | G18: 2000
A19: Себестоимость событий (вкл. 50% площадке) | B19: % | C19: 0.65 | D19: 0.65 | E19: 0.65 | F19: 0.65 | G19: 0.65
A20: Доля участников, купивших мерч в месяц | B20: % | C20: 0.03 | D20: 0.03 | E20: 0.03 | F20: 0.03 | G20: 0.03
A21: Доля MAU, купивших мерч в месяц | B21: % | C21: 0.001 | D21: 0.001 | E21: 0.001 | F21: 0.001 | G21: 0.001
A22: Средний чек мерча | B22: ₽ | C22: 2500 | D22: 2500 | E22: 2500 | F22: 2500 | G22: 2500
A23: Себестоимость мерча | B23: % | C23: 0.45 | D23: 0.45 | E23: 0.45 | F23: 0.45 | G23: 0.45
A24: Разборов ЦФА в год (80 000 ₽) | B24: шт | C24: 1 | D24: 2 | E24: 4 | F24: 6 | G24: 10 | H24: личная экспертиза, отдельный контур
A25: Сборок выпуска в год (325 000 ₽) | B25: шт | C25: 0 | D25: 1 | E25: 2 | F25: 3 | G25: 5 | H25: середина 250–400 тыс.
A26: Подписчиков YuRichRWA | B26: чел | C26: 1000 | D26: 2000 | E26: 5000 | F26: 10000 | G26: 20000
A27: Охват поста YuRichRWA | B27: % | C27: 0.3 | D27: 0.3 | E27: 0.3 | F27: 0.3 | G27: 0.3
A28: CPM ниши RWA | B28: ₽ | C28: 1500 | D28: 1500 | E28: 1500 | F28: 1500 | G28: 1500
A29: Рекламных постов YuRichRWA в месяц | B29: шт | C29: 0 | D29: 1 | E29: 3 | F29: 5 | G29: 8
A30: Сервер, домены, сервисы | B30: ₽/мес | C30: 1500 | D30: 2500 | E30: 6000 | F30: 15000 | G30: 40000
A31: AI (Кира) на 1 MAU | B31: ₽ | C31: 0 | D31: 0 | E31: 3 | F31: 3 | G31: 3 | H31: с S3
A32: Команда | B32: ₽/мес | C32: 0 | D32: 30000 | E32: 140000 | F32: 400000 | G32: 1200000 | H32: S1 — всё сам
A33: Маркетинг: посевы, QR, печать | B33: ₽/мес | C33: 10000 | D33: 30000 | E33: 100000 | F33: 200000 | G33: 600000
A34: Бухгалтерия и юрист | B34: ₽/мес | C34: 5000 | D34: 10000 | E34: 20000 | F34: 40000 | G34: 100000
A35: Товарный знак, ПО, БД (разово / 12) | B35: ₽/мес | C35: 12500 | D35: 12500 | E35: 0 | F35: 0 | G35: 25000
A36: Часы на контент | B36: ч | C36: 20 | D36: 30 | E36: 60 | F36: 100 | G36: 250
A37: CITY CODE
A38: Спрос на членство | B38: чел | C38: =C7*C9+C10 | D38: =D7*D9+D10 | E38: =E7*E9+E10 | F38: =F7*F9+F10 | G38: =G7*G9+G10
A39: Потолок по партнёрам (15 на точку) | B39: чел | C39: =C6*'Расчёт'!$D$37 | D39: =D6*'Расчёт'!$D$37 | E39: =E6*'Расчёт'!$D$37 | F39: =F6*'Расчёт'!$D$37 | G39: =G6*'Расчёт'!$D$37
A40: Участников | B40: чел | C40: =ROUND(MIN(C38,C39),0) | D40: =ROUND(MIN(D38,D39),0) | E40: =ROUND(MIN(E38,E39),0) | F40: =ROUND(MIN(F38,F39),0) | G40: =ROUND(MIN(G38,G39),0)
A41: из них «Основатели» | B41: чел | C41: =MIN(C8,C40) | D41: =MIN(D8,D40) | E41: =MIN(E8,E40) | F41: =MIN(F8,F40) | G41: =MIN(G8,G40)
A42: из них Basic | B42: чел | C42: =C40-C41 | D42: =D40-D41 | E42: =E40-E41 | F42: =F40-F41 | G42: =G40-G41
A43: Выручка членства | B43: ₽/мес | C43: =(C41*'Параметры'!$D$4+C42*'Параметры'!$D$3)/12 | D43: =(D41*'Параметры'!$D$4+D42*'Параметры'!$D$3)/12 | E43: =(E41*'Параметры'!$D$4+E42*'Параметры'!$D$3)/12 | F43: =(F41*'Параметры'!$D$4+F42*'Параметры'!$D$3)/12 | G43: =(G41*'Параметры'!$D$4+G42*'Параметры'!$D$3)/12
A44: Оборот клуба у партнёров (не наш доход) | B44: ₽/мес | C44: =C40*'Параметры'!$D$11 | D44: =D40*'Параметры'!$D$11 | E44: =E40*'Параметры'!$D$11 | F44: =F40*'Параметры'!$D$11 | G44: =G40*'Параметры'!$D$11
A45: на одного партнёра | B45: ₽/мес | C45: =C44/C6 | D45: =D44/D6 | E45: =E44/E6 | F45: =F44/F6 | G45: =G44/G6
A46: ДРУГИЕ ДОХОДЫ
A47: Взнос партнёров v2.0 (если решишь) | B47: ₽/мес | C47: =C6*C11 | D47: =D6*D11 | E47: =E6*E11 | F47: =F6*F11 | G47: =G6*G11
A48: Средний чек размещения | B48: ₽ | C48: =MAX('Параметры'!$D$45,ROUND(C13*'Параметры'!$D$44/1000,-2))*(1-C14*'Параметры'!$D$51) | D48: =MAX('Параметры'!$D$45,ROUND(D13*'Параметры'!$D$44/1000,-2))*(1-D14*'Параметры'!$D$51) | E48: =MAX('Параметры'!$D$45,ROUND(E13*'Параметры'!$D$44/1000,-2))*(1-E14*'Параметры'!$D$51) | F48: =MAX('Параметры'!$D$45,ROUND(F13*'Параметры'!$D$44/1000,-2))*(1-F14*'Параметры'!$D$51) | G48: =MAX('Параметры'!$D$45,ROUND(G13*'Параметры'!$D$44/1000,-2))*(1-G14*'Параметры'!$D$51)
A49: Реклама SAI | B49: ₽/мес | C49: =C12*C48 | D49: =D12*D48 | E49: =E12*E48 | F49: =F12*F48 | G49: =G12*G48
A50: Съёмки | B50: ₽/мес | C50: =C15*'Параметры'!$D$52 | D50: =D15*'Параметры'!$D$52 | E50: =E15*'Параметры'!$D$52 | F50: =F15*'Параметры'!$D$52 | G50: =G15*'Параметры'!$D$52
A51: События | B51: ₽/мес | C51: =C16*C17*C18 | D51: =D16*D17*D18 | E51: =E16*E17*E18 | F51: =F16*F17*F18 | G51: =G16*G17*G18
A52: Мерч | B52: ₽/мес | C52: =(C40*C20+C7*C21)*C22 | D52: =(D40*D20+D7*D21)*D22 | E52: =(E40*E20+E7*E21)*E22 | F52: =(F40*F20+F7*F21)*F22 | G52: =(G40*G20+G7*G21)*G22
A53: ЦФА-услуги (среднемесячно) | B53: ₽/мес | C53: =(C24*80000+C25*325000)/12 | D53: =(D24*80000+D25*325000)/12 | E53: =(E24*80000+E25*325000)/12 | F53: =(F24*80000+F25*325000)/12 | G53: =(G24*80000+G25*325000)/12
A54: Реклама YuRichRWA | B54: ₽/мес | C54: =C26*C27*C28/1000*C29 | D54: =D26*D27*D28/1000*D29 | E54: =E26*E27*E28/1000*E29 | F54: =F26*F27*F28/1000*F29 | G54: =G26*G27*G28/1000*G29
A55: ВСЯ ВЫРУЧКА | B55: ₽/мес | C55: =C43+C47+C49+C50+C51+C52+C53+C54 | D55: =D43+D47+D49+D50+D51+D52+D53+D54 | E55: =E43+E47+E49+E50+E51+E52+E53+E54 | F55: =F43+F47+F49+F50+F51+F52+F53+F54 | G55: =G43+G47+G49+G50+G51+G52+G53+G54
A56: Выручка за год | B56: ₽/год | C56: =C55*12 | D56: =D55*12 | E56: =E55*12 | F56: =F55*12 | G56: =G55*12
A57: РАСХОДЫ
A58: AI (Кира) | B58: ₽/мес | C58: =C7*C31 | D58: =D7*D31 | E58: =E7*E31 | F58: =F7*F31 | G58: =G7*G31
A59: Приём платежей | B59: ₽/мес | C59: ='Расчёт'!$D$8*(C43+C51+C52) | D59: ='Расчёт'!$D$8*(D43+D51+D52) | E59: ='Расчёт'!$D$8*(E43+E51+E52) | F59: ='Расчёт'!$D$8*(F43+F51+F52) | G59: ='Расчёт'!$D$8*(G43+G51+G52)
A60: Себестоимость событий, мерча, съёмок | B60: ₽/мес | C60: =C51*C19+C52*C23+C50*'Параметры'!$D$54 | D60: =D51*D19+D52*D23+D50*'Параметры'!$D$54 | E60: =E51*E19+E52*E23+E50*'Параметры'!$D$54 | F60: =F51*F19+F52*F23+F50*'Параметры'!$D$54 | G60: =G51*G19+G52*G23+G50*'Параметры'!$D$54
A61: Сбор 3% с рекламы | B61: ₽/мес | C61: ='Параметры'!$D$33*(C49+C54) | D61: ='Параметры'!$D$33*(D49+D54) | E61: ='Параметры'!$D$33*(E49+E54) | F61: ='Параметры'!$D$33*(F49+F54) | G61: ='Параметры'!$D$33*(G49+G54)
A62: Взносы ИП за себя | B62: ₽/мес | C62: =('Параметры'!$D$26+MAX(0,C56-'Параметры'!$D$28)*'Параметры'!$D$27)/12 | D62: =('Параметры'!$D$26+MAX(0,D56-'Параметры'!$D$28)*'Параметры'!$D$27)/12 | E62: =('Параметры'!$D$26+MAX(0,E56-'Параметры'!$D$28)*'Параметры'!$D$27)/12 | F62: =('Параметры'!$D$26+MAX(0,F56-'Параметры'!$D$28)*'Параметры'!$D$27)/12 | G62: =('Параметры'!$D$26+MAX(0,G56-'Параметры'!$D$28)*'Параметры'!$D$27)/12
A63: УСН 6% минус взносы | B63: ₽/мес | C63: =MAX(0,C55*'Параметры'!$D$25-C62) | D63: =MAX(0,D55*'Параметры'!$D$25-D62) | E63: =MAX(0,E55*'Параметры'!$D$25-E62) | F63: =MAX(0,F55*'Параметры'!$D$25-F62) | G63: =MAX(0,G55*'Параметры'!$D$25-G62)
A64: ВСЕ РАСХОДЫ | B64: ₽/мес | C64: =C30+C58+C32+C33+C34+C35+C62+C59+C60+C61+C63 | D64: =D30+D58+D32+D33+D34+D35+D62+D59+D60+D61+D63 | E64: =E30+E58+E32+E33+E34+E35+E62+E59+E60+E61+E63 | F64: =F30+F58+F32+F33+F34+F35+F62+F59+F60+F61+F63 | G64: =G30+G58+G32+G33+G34+G35+G62+G59+G60+G61+G63
A65: РЕЗУЛЬТАТ
A66: Прибыль в месяц (без зарплаты основателя) | B66: ₽/мес | C66: =C55-C64 | D66: =D55-D64 | E66: =E55-E64 | F66: =F55-F64 | G66: =G55-G64
A67: Прибыль за год | B67: ₽/год | C67: =C66*12 | D67: =D66*12 | E67: =E66*12 | F67: =F66*12 | G67: =G66*12
A68: Прибыль города без ЦФА-услуг | B68: ₽/мес | C68: =C66-C53*(1-'Параметры'!$D$25) | D68: =D66-D53*(1-'Параметры'!$D$25) | E68: =E66-E53*(1-'Параметры'!$D$25) | F68: =F66-F53*(1-'Параметры'!$D$25) | G68: =G66-G53*(1-'Параметры'!$D$25)
A69: …и без взноса партнёров (строго v1.0) | B69: ₽/мес | C69: =C68-C47*(1-'Параметры'!$D$25) | D69: =D68-D47*(1-'Параметры'!$D$25) | E69: =E68-E47*(1-'Параметры'!$D$25) | F69: =F68-F47*(1-'Параметры'!$D$25) | G69: =G68-G47*(1-'Параметры'!$D$25)
A70: Часов работы в месяц | B70: ч | C70: =(C7*0.02+C40*0.1)*0.25+C6*3+C7*0.01*0.2+C36+C16*12 | D70: =(D7*0.02+D40*0.1)*0.25+D6*3+D7*0.01*0.2+D36+D16*12 | E70: =(E7*0.02+E40*0.1)*0.25+E6*3+E7*0.01*0.2+E36+E16*12 | F70: =(F7*0.02+F40*0.1)*0.25+F6*3+F7*0.01*0.2+F36+F16*12 | G70: =(G7*0.02+G40*0.1)*0.25+G6*3+G7*0.01*0.2+G36+G16*12
A71: Людей на полный день (160 ч) | B71: чел | C71: =C70/160 | D71: =D70/160 | E71: =E70/160 | F71: =F70/160 | G71: =G70/160

Sheet XP
A1: Дней до порога XP — прогон типовых людей на НАСТОЯЩЕМ коде бота (economics/xp_simulator.py)
A3: v1.1 — после патча бота
A4: Профиль | B4: 100 · Житель | C4: 300 · Исследователь | D4: 800 · Проводник | E4: 2000 · Амбассадор | F4: 4000 · Легенда города | G4: 7000 · City Code
A5: Турист / редкий гость | B5: 119 | C5: 399 | D5: 1099 | E5: > 6 лет | F5: > 6 лет | G5: > 6 лет
A6: Житель: заходит 3 раза в неделю | B6: 37 | C6: 133 | D6: 365 | E6: 925 | F6: 1857 | G6: > 6 лет
A7: Активный: 5 дней в неделю, всё меню | B7: 10 | C7: 38 | D7: 108 | E7: 276 | F7: 556 | G7: 976
A8: Фармер кнопок: каждый день все 8 действий | B8: 8 | C8: 28 | D8: 78 | E8: 198 | F8: 398 | G8: 698
A9: Вкладчик города: активный + 2 места + 1 событие + 1 друг в месяц | B9: 3 | C9: 10 | D9: 43 | E9: 123 | F9: 246 | G9: 438
A10: Амбассадор: вкладчик + 4 места + 2 события + 3 друга в месяц | B10: 3 | C10: 10 | D10: 29 | E10: 78 | F10: 153 | G10: 273
A11: Партнёр-точка: житель + узел подключён (+200) и жив каждый месяц (+80) | B11: 3 | C11: 33 | D11: 123 | E11: 385 | F11: 793 | G11: 1413
A13: v1.0 — код бота до патча
A14: Профиль | B14: 100 · Житель | C14: 300 · Исследователь | D14: 800 · Проводник | E14: 2000 · Амбассадор | F14: 4000 · Легенда города | G14: 7000 · City Code
A15: Турист / редкий гость | B15: 84 | C15: 287 | D15: 784 | E15: 1988 | F15: > 6 лет | G15: > 6 лет
A16: Житель: заходит 3 раза в неделю | B16: 28 | C16: 93 | D16: 260 | E16: 660 | F16: 1325 | G16: > 6 лет
A17: Активный: 5 дней в неделю, всё меню | B17: 7 | C17: 25 | D17: 72 | E17: 184 | F17: 371 | G17: 651
A18: Фармер кнопок: каждый день все 8 действий | B18: 4 | C18: 13 | D18: 35 | E18: 90 | F18: 181 | G18: 317
A19: Вкладчик города: активный + 2 места + 1 событие + 1 друг в месяц | B19: 3 | C19: 10 | D19: 40 | E19: 112 | F19: 225 | G19: 396
A20: Амбассадор: вкладчик + 4 места + 2 события + 3 друга в месяц | B20: 3 | C20: 10 | D20: 29 | E20: 77 | F20: 152 | G20: 268
A21: Партнёр-точка: житель + узел подключён (+200) и жив каждый месяц (+80) | B21: 3 | C21: 28 | D21: 113 | E21: 329 | F21: 673 | G21: 1203

Sheet Доли партнёров
A1: Калькулятор долей: динамическая модель (Slicing Pie)
A2: Вклад считается по рыночной цене. Неоплаченное время и ресурсы ×2, живые деньги ×4 (риск выше). Доля = вклад участника / сумма вкладов. Итог — ориентир для переговоров, а не автоматическое решение.
A4: Участник | B4: Роль | C4: Неоплач. время, ₽/мес (рынок) | D4: Ресурсы, ₽/мес (аренда по рынку) | E4: Месяцев | F4: Разовый вклад (IP, оборудование), ₽ | G4: Деньги, ₽ | H4: Вклад (слайсы) | I4: Доля
A5: YuRich (основатель) | B5: Продукт, бренд, бот, база, сайт, продажи | C5: 150000 | D5: 0 | E5: 12 | F5: 1500000 | G5: 300000 | H5: =2*(C5+D5)*E5+2*F5+4*G5 | I5: =IF(SUM($H$5:$H$8)=0,0,H5/SUM($H$5:$H$8))
A6: Партнёр по оборудованию и контенту | B6: Камера, свет, звук, монтаж, съёмки | C6: 0 | D6: 40000 | E6: 12 | F6: 0 | G6: 0 | H6: =2*(C6+D6)*E6+2*F6+4*G6 | I6: =IF(SUM($H$5:$H$8)=0,0,H6/SUM($H$5:$H$8))
A7: Партнёр по событиям и офису | B7: Площадка для событий, рабочее место | C7: 0 | D7: 60000 | E7: 12 | F7: 0 | G7: 0 | H7: =2*(C7+D7)*E7+2*F7+4*G7 | I7: =IF(SUM($H$5:$H$8)=0,0,H7/SUM($H$5:$H$8))
A8: (резерв) Технический партнёр | B8: Разработка, сервер | C8: 0 | D8: 0 | E8: 0 | F8: 0 | G8: 0 | H8: =2*(C8+D8)*E8+2*F8+4*G8 | I8: =IF(SUM($H$5:$H$8)=0,0,H8/SUM($H$5:$H$8))
G9: Итого | H9: =SUM(H5:H8) | I9: =SUM(I5:I8)
A11: Ограничители (рекомендация)
A12: 1. Пул стратегических партнёров — не больше 10–15% на всех. Если калькулятор даёт больше — излишек платим revenue share, а не долей.
A13: 2. Вестинг 24–36 месяцев, первые 6–12 месяцев «клифф»: ушёл раньше — доли нет, вклад закрываем выплатами по выручке.
A14: 3. Доля возможна только в юрлице (ООО). Пока ты физлицо/ИП — опционный договор (ст. 429.2 ГК) или договор о выручке.
A15: 4. Доля — в той компании, где лежат права (товарные знаки, ПО, база). Не дробить на «долю в боте» и «долю в клубе».
A16: 5. Revenue share вместо доли: партнёру по оборудованию — 40% выручки со съёмок (= shoot_cost в params.json), площадке — 50% чистой выручки события.
